bzenet.cp37-win_amd64.pyd
bzenet-0.1.5.dist-info/LICENSE
bzenet-0.1.5.dist-info/METADATA
bzenet-0.1.5.dist-info/WHEEL
bzenet-0.1.5.dist-info/top_level.txt
bzenet-0.1.5.dist-info/RECORD
