Metadata-Version: 2.1
Name: bzenet
Version: 0.1.5
Summary: A python wrapper for the ENet library ver. 1.3.14
Home-page: https://github.com/smile4u/bzenet
Maintainer: Sergey Zdanevich, BlitzTeam
Maintainer-email: sergey.zdanevich@blitzteam.com
License: UNKNOWN
Platform: UNKNOWN
License-File: LICENSE
Requires-Dist: Cython (<1,>=0)
